HDL_1.v
// GATE LEVEL MODELING

module HDL_1 (input A, B, C, D, output F);
    wire AC, BC, CC, DC; 
    wire w1, w2, w3, w4, w5, w6, w7, w8, w9;

    // Generate Complements
    not G1(AC, A);
    not G2(BC, B);
    not G3(CC, C);
    not G4(DC, D);

    // Minterm Implementation (Fixed AND Gates)
    and G5(w1, AC, BC, CC, DC); // 0
    and G6(w2, AC, BC, CC, D);  // 1
    and G7(w3, A, BC, CC, DC);  // 8
    and G8(w4, A, BC, CC, D);   // 9
    and G9(w5, A, BC, C, D);    // 10
    and G10(w6, A, BC, C, DC);  // 11
    and G11(w7, A, B, CC, DC);  // 12
    and G12(w8, A, B, C, DC);   // 14
    and G13(w9, A, B, C, D);    // 15

    // OR Gate to Sum Minterms
    or G14(F, w1, w2, w3, w4, w5, w6, w7, w8, w9);
endmodule

HDL_1_tb.v
`timescale 1ns / 1ns

module HDL_1_tb();
    reg [3:0] t_input;
    wire t_E;
    integer i;

    HDL_1 dut(.A(t_input[3]),.B(t_input[2]),
                .C(t_input[1]), .D(t_input[0]),.F(t_Output));

    initial begin
        t_input = 4'b0000;
        for (i = 0; i < 16; i = i + 1) 
        begin
            #10 t_input = i; 
        end
    end

    initial begin
        $display("Sum of Minterm: F(W,X,Y,Z) = m(0,1,8,9,10,11,12,14,15)");
    end

    initial begin
        $monitor("time = %0d, \t A= %b, B= %b, C= %b, D= %b, \t E (Output)= %b", 
                 $time, t_input[3], t_input[2], t_input[1], t_input[0], t_Output);
        $dumpfile("HDL_1.vcd");  
        $dumpvars(0, HDL_1_tb);  
    end
endmodule

HDL_1.vcd
$date
	Tue Feb 11 00:34:42 2025
$end
$version
	Icarus Verilog
$end
$timescale
	1ns
$end
$scope module HDL_1_tb $end
$var wire 1 ! t_Output $end
$var reg 4 " t_input [3:0] $end
$var integer 32 # i [31:0] $end
$scope module dut $end
$var wire 1 $ A $end
$var wire 1 % AC $end
$var wire 1 & B $end
$var wire 1 ' BC $end
$var wire 1 ( C $end
$var wire 1 ) CC $end
$var wire 1 * D $end
$var wire 1 + DC $end
$var wire 1 ! F $end
$var wire 1 , w1 $end
$var wire 1 - w2 $end
$var wire 1 . w3 $end
$var wire 1 / w4 $end
$var wire 1 0 w5 $end
$var wire 1 1 w6 $end
$var wire 1 2 w7 $end
$var wire 1 3 w8 $end
$var wire 1 4 w9 $end
$upscope $end
$upscope $end
$enddefinitions $end
$comment Show the parameter values. $end
$dumpall
$end
#0
$dumpvars
04
03
02
01
00
0/
0.
0-
1,
1+
0*
1)
0(
1'
0&
1%
0$
b0 #
b0 "
1!
$end
#10
b1 #
#20
0,
0+
1-
1*
b10 #
b1 "
#30
0!
0)
1+
0-
1(
0*
b11 #
b10 "
#40
0+
1*
b100 #
b11 "
#50
0'
1)
1+
1&
0(
0*
b101 #
b100 "
#60
0+
1*
b110 #
b101 "
#70
0)
1+
1(
0*
b111 #
b110 "
#80
0+
1*
b1000 #
b111 "
#90
1!
0%
1.
1'
1)
1+
1$
0&
0(
0*
b1001 #
b1000 "
#100
0.
0+
1/
1*
b1010 #
b1001 "
#110
0)
11
1+
0/
1(
0*
b1011 #
b1010 "
#120
01
0+
10
1*
b1100 #
b1011 "
#130
0'
12
1)
1+
00
1&
0(
0*
b1101 #
b1100 "
#140
0!
02
0+
1*
b1110 #
b1101 "
#150
1!
0)
13
1+
1(
0*
b1111 #
b1110 "
#160
03
0+
14
1*
b10000 #
b1111 "
