ACatF.v
// Francesca Anne Denise C. Catolico - CSARCH1 XX22
// Behavioral Odd Up-Down Counter using JK Flip-Flops

module OddUpDownCounter(
    input clk,
    input reset,
    input Y,
    output reg [3:0] out
);

// State transitions
always @(posedge clk or negedge reset) begin
    if (!reset) begin
        out <= 4'b0001; // Reset condition
    end
    else begin
        if (Y) begin
            // Upstream transition (0001 → 0011 → ... → 1111 → 0001)
            case(out)
                4'b0001: out <= 4'b0011;
                4'b0011: out <= 4'b0101;
                4'b0101: out <= 4'b0111;
                4'b0111: out <= 4'b1001;
                4'b1001: out <= 4'b1011;
                4'b1011: out <= 4'b1101;
                4'b1101: out <= 4'b1111;
                4'b1111: out <= 4'b0001;
                default: out <= 4'b0001;
            endcase
        end
        else begin
            // Downstream transition (1111 → 1101 → ... → 0001 → 1111)
            case(out)
                4'b1111: out <= 4'b1101;
                4'b1101: out <= 4'b1011;
                4'b1011: out <= 4'b1001;
                4'b1001: out <= 4'b0111;
                4'b0111: out <= 4'b0101;
                4'b0101: out <= 4'b0011;
                4'b0011: out <= 4'b0001;
                4'b0001: out <= 4'b1111;
                default: out <= 4'b1111;
            endcase
        end
    end
end

endmodule

ACatF_tb.v
// Francesca Anne Denise C. Catolico - CSARCH1 XX22
// Testbench for OddUpDownCounter

`timescale 1ns/1ns
module OddUpDownCounter_tb;
    reg clk, reset, Y;
    wire [3:0] out;
    
    // Instantiate the counter
    OddUpDownCounter uut(.clk(clk), .reset(reset), .Y(Y), .out(out));
    
    // Clock generation (5 time units half cycle)
    initial begin
        clk = 0;
        forever #5 clk = ~clk;
    end
    
    // Test cases
    initial begin
        // Initial reset
        reset = 0; Y = 0;
        #10 reset = 1; // Release reset after 10ns
        
        // Test downstream (Y=0)
        Y = 0;
        #100; // Allow time to see transitions
        
        // Test upstream (Y=1)
        Y = 1;
        #100;
        
        $finish;
    end
    
    // Monitor signals
    initial begin
        $monitor("Time=%t, clk=%b, reset=%b, Y=%b, out=%b, Decimal: %d", 
                 $time, clk, reset, Y, out, out);
    end
    
    // Generate waveform file
    initial begin
        $dumpfile("waveform.vcd");
        $dumpvars(0, OddUpDownCounter_tb);
    end
endmodule

waveform.vcd
$date
	Sun Apr 06 11:21:20 2025
$end
$version
	Icarus Verilog
$end
$timescale
	1ns
$end
$scope module OddUpDownCounter_tb $end
$var wire 4 ! out [3:0] $end
$var reg 1 " Y $end
$var reg 1 # clk $end
$var reg 1 $ reset $end
$scope module uut $end
$var wire 1 " Y $end
$var wire 1 # clk $end
$var wire 1 $ reset $end
$var reg 4 % out [3:0] $end
$upscope $end
$upscope $end
$enddefinitions $end
$comment Show the parameter values. $end
$dumpall
$end
#0
$dumpvars
b1 %
0$
0#
0"
b1 !
$end
#5
1#
#10
0#
1$
#15
b1111 !
b1111 %
1#
#20
0#
#25
b1101 !
b1101 %
1#
#30
0#
#35
b1011 !
b1011 %
1#
#40
0#
#45
b1001 !
b1001 %
1#
#50
0#
#55
b111 !
b111 %
1#
#60
0#
#65
b101 !
b101 %
1#
#70
0#
#75
b11 !
b11 %
1#
#80
0#
#85
b1 !
b1 %
1#
#90
0#
#95
b1111 !
b1111 %
1#
#100
0#
#105
b1101 !
b1101 %
1#
#110
0#
1"
#115
b1111 !
b1111 %
1#
#120
0#
#125
b1 !
b1 %
1#
#130
0#
#135
b11 !
b11 %
1#
#140
0#
#145
b101 !
b101 %
1#
#150
0#
#155
b111 !
b111 %
1#
#160
0#
#165
b1001 !
b1001 %
1#
#170
0#
#175
b1011 !
b1011 %
1#
#180
0#
#185
b1101 !
b1101 %
1#
#190
0#
#195
b1111 !
b1111 %
1#
#200
0#
#205
b1 !
b1 %
1#
