FINAL MP/RStrA.v
// Adler Clarence E. Strebel - S17

`timescale 1ns / 1ps

module HDL_1_dataflow (F,A,B,C,D);
    input A,B,C,D;
    input w1,w2,w3,w4,w5,w6,w7,w8,w9;
    output F;

    assign w1 = ~A&~B&~C&~D;    //0
    assign w2 = ~A&~B&~C&D;     //1
    assign w3 = A&~B&~C&~D;     //8
    assign w4 = A&~B&~C&D;      //9
    assign w5 = A&~B&C&~D;      //10
    assign w6 = A&~B&C&D;       //11
    assign w7 = A&B&~C&~D;      //12 
    assign w8 = A&B&C&~D;       //14  
    assign w9 = A&B&C&D;        //15

    assign F = w1 | w2 | w3 | w4 | w5 | w6 | w7 | w8 | w9;
endmodule

FINAL MP/RStrA_tb.v
// Adler Clarence E. Strebel - S17

`timescale 1ns / 1ps

module HDL_1_tb();
    reg [3:0] t_input;
    wire t_Output;
    integer i;

    HDL_1_dataflow dut(t_Output, t_input[3], t_input[2], t_input[1], t_input[0]);

    initial begin
        t_input = 4'b0000;
        for (i = 1; i <= 16; i = i + 1) 
        begin
            #10 t_input = i; 
        end
    end

    initial begin
        $display("Adler Clarence E. Strebel | CSARCH1 S17 | Dataflow");
        $display("Sum of Minterm: F(W,X,Y,Z) = m(0,1,8,9,10,11,12,14,15)");
    end

    initial begin
        $monitor("time = %0d \t A= %b, B= %b, C= %b, D= %b \t E (Output)= %b", 
                 $time, t_input[3], t_input[2], t_input[1], t_input[0], t_Output);
        $dumpfile("RStrA");  
        $dumpvars(0, HDL_1_tb); 
    end
endmodule

FINAL MP/RStrA.vcd
$date
	Thu Feb 13 20:41:01 2025
$end
$version
	Icarus Verilog
$end
$timescale
	1ps
$end
$scope module HDL_1_tb $end
$var wire 1 ! t_Output $end
$var reg 4 " t_input [3:0] $end
$var integer 32 # i [31:0] $end
$scope module dut $end
$var wire 1 $ A $end
$var wire 1 % B $end
$var wire 1 & C $end
$var wire 1 ' D $end
$var wire 1 ! F $end
$var wire 1 ( w1 $end
$var wire 1 ) w2 $end
$var wire 1 * w3 $end
$var wire 1 + w4 $end
$var wire 1 , w5 $end
$var wire 1 - w6 $end
$var wire 1 . w7 $end
$var wire 1 / w8 $end
$var wire 1 0 w9 $end
$upscope $end
$upscope $end
$enddefinitions $end
$comment Show the parameter values. $end
$dumpall
$end
#0
$dumpvars
00
0/
0.
0-
0,
0+
0*
0)
1(
0'
0&
0%
0$
b1 #
b0 "
1!
$end
#10000
0(
1)
1'
b10 #
b1 "
#20000
0!
0(
0)
1&
0'
b11 #
b10 "
#30000
1'
b100 #
b11 "
#40000
0!
0(
1%
0&
0'
b101 #
b100 "
#50000
1'
b110 #
b101 "
#60000
1&
0'
b111 #
b110 "
#70000
1'
b1000 #
b111 "
#80000
1!
1*
1$
0%
0&
0'
b1001 #
b1000 "
#90000
0*
1+
1'
b1010 #
b1001 "
#100000
0*
1,
0+
1&
0'
b1011 #
b1010 "
#110000
0,
1-
1'
b1100 #
b1011 "
#120000
1!
0*
1.
0-
1%
0&
0'
b1101 #
b1100 "
#130000
0!
0.
1'
b1110 #
b1101 "
#140000
1!
0.
1/
1&
0'
b1111 #
b1110 "
#150000
0/
10
1'
b10000 #
b1111 "
#160000
1(
1!
00
0$
0%
0&
0'
b10001 #
b0 "
