test-codes/sample_circuit.v


module sample_circuit (input A, B, C, output D, E);
    wire w1;

    and G1(w1, A, B);
    not G2(E, C);
    or G3(D, w1, E);
endmodule

test-codes/sample_circuit_tb.v
`timescale 1ns / 1ps

module sample_circuit_tb();
    reg t_A, t_B, t_C; // reg..input
    wire t_D, t_E;      // wire..output

    sample_circuit dut(t_A, t_B, t_C, t_D, t_E);

    initial begin

        t_A = 0;
        t_B = 0; 
        t_C = 0;

        #10 t_A = 0; t_B = 0; t_C = 1;
        #10 t_A = 0; t_B = 1; t_C = 0;
        #10 t_A = 0; t_B = 1; t_C = 1;
        #10 t_A = 1; t_B = 0; t_C = 0;
        #10 t_A = 1; t_B = 0; t_C = 1;
        #10 t_A = 1; t_B = 1; t_C = 0;
        #10 t_A = 1; t_B = 1; t_C = 1;
    end

    // Monitor block to observe outputs
    initial begin
        $monitor("time = %0d, A = %b, B = %b, C = %b, D = %b, E = %b", $time, t_A, t_B, t_C, t_D, t_E);
        $dumpfile("sample_circuit.vcd");  // Output file for waveform
        $dumpvars(0, sample_circuit_tb);  // Dump all signals for waveform analysis
    end
endmodule

test-codes/sample_circuit.vcd
$date
	Mon Feb 10 21:51:23 2025
$end
$version
	Icarus Verilog
$end
$timescale
	1ps
$end
$scope module sample_circuit_tb $end
$var wire 1 ! t_E $end
$var wire 1 " t_D $end
$var reg 1 # t_A $end
$var reg 1 $ t_B $end
$var reg 1 % t_C $end
$scope module dut $end
$var wire 1 # A $end
$var wire 1 $ B $end
$var wire 1 % C $end
$var wire 1 " D $end
$var wire 1 ! E $end
$var wire 1 & w1 $end
$upscope $end
$upscope $end
$enddefinitions $end
$comment Show the parameter values. $end
$dumpall
$end
#0
$dumpvars
0&
0%
0$
0#
1"
1!
$end
#10000
0"
0!
1%
#20000
1"
1!
0%
1$
#30000
0"
0!
1%
#40000
1"
1!
0%
0$
1#
#50000
0"
0!
1%
#60000
1"
1!
1&
0%
1$
#70000
0!
1%
