HDL2/AStrA.v
// Adler Clarence E. Strebel - CSARCH1 S17
// Behavioral Model Odd Up-Down Binary Counter using T Flip-Flop

module AStrA(Q, Y, clk, rst);
    output reg [3:0] Q;
    input Y, clk, rst;
    
    parameter S0 = 4'b0001;  // 1
    parameter S1 = 4'b0011;  // 3
    parameter S2 = 4'b0101;  // 5
    parameter S3 = 4'b0111;  // 7
    parameter S4 = 4'b1001;  // 9
    parameter S5 = 4'b1011;  // 11
    parameter S6 = 4'b1101;  // 13
    parameter S7 = 4'b1111;  // 15
    
    reg [3:0] next_state;
    
    always @(posedge clk, negedge rst) 
    begin
        if (rst == 0) 
            Q <= S0;  //0001 | 1
        else 
            Q <= next_state;
    end
    
    always @(Q, Y) 
    begin
        case(Q)
            S0: if(Y == 1) next_state = S1; else next_state = S7;  // 1->3 or 1->15
            S1: if(Y == 1) next_state = S2; else next_state = S0;  // 3->5 or 3->1
            S2: if(Y == 1) next_state = S3; else next_state = S1;  // 5->7 or 5->3
            S3: if(Y == 1) next_state = S4; else next_state = S2;  // 7->9 or 7->5
            S4: if(Y == 1) next_state = S5; else next_state = S3;  // 9->11 or 9->7
            S5: if(Y == 1) next_state = S6; else next_state = S4;  // 11->13 or 11->9
            S6: if(Y == 1) next_state = S7; else next_state = S5;  // 13->15 or 13->11
            S7: if(Y == 1) next_state = S0; else next_state = S6;  // 15->1 or 15->13
        endcase
    end
endmodule

HDL2/AStrA_tb.v
// Adler Clarence E. Strebel - CSARCH1 S17
// Testbench for Odd Up-Down Binary Counter using T Flip-Flop

`timescale 1ns/1ns  

module AStrA_tb();
    reg t_Y;
    reg t_clk;
    reg t_rst;
    wire [3:0] t_Q;
    
    AStrA dut(t_Q, t_Y, t_clk, t_rst);
    
    initial 
    begin
        t_clk = 1'b0;
        forever #5 t_clk = ~t_clk;
    end
    
    initial 
    begin
        t_rst = 1'b0; 
        #10 t_rst = 1'b1;  
    end
    
    initial 
    begin
        t_Y = 1'b0;
        #100 t_Y = 1'b1;  
    end
    
    initial 
    begin
        $display("Program by Adler Clarence E. Strebel,  Behavioral Odd Up_Down BCD counter using T Flip Flop");
        $monitor("time=%3d, | clk:%b, | rst:%b, | Y:%b, | Q:%b (%0d)", $time, t_clk, t_rst, t_Y, t_Q, t_Q);
        $dumpfile("AStrA.vcd");
        $dumpvars();
    end
    initial #190 $finish;
endmodule

HDL2/AStrA.vcd
$date
	Sun Apr 06 19:39:26 2025
$end
$version
	Icarus Verilog
$end
$timescale
	1ns
$end
$scope module AStrA_tb $end
$var wire 4 ! t_Q [3:0] $end
$var reg 1 " t_Y $end
$var reg 1 # t_clk $end
$var reg 1 $ t_rst $end
$scope module dut $end
$var wire 1 " Y $end
$var wire 1 # clk $end
$var wire 1 $ rst $end
$var parameter 4 % S0 $end
$var parameter 4 & S1 $end
$var parameter 4 ' S2 $end
$var parameter 4 ( S3 $end
$var parameter 4 ) S4 $end
$var parameter 4 * S5 $end
$var parameter 4 + S6 $end
$var parameter 4 , S7 $end
$var reg 4 - Q [3:0] $end
$var reg 4 . next_state [3:0] $end
$upscope $end
$upscope $end
$enddefinitions $end
$comment Show the parameter values. $end
$dumpall
b1111 ,
b1101 +
b1011 *
b1001 )
b111 (
b101 '
b11 &
b1 %
$end
#0
$dumpvars
b1111 .
b1 -
0$
0#
0"
b1 !
$end
#5
1#
#10
0#
1$
#15
b1101 .
b1111 !
b1111 -
1#
#20
0#
#25
b1011 .
b1101 !
b1101 -
1#
#30
0#
#35
b1001 .
b1011 !
b1011 -
1#
#40
0#
#45
b111 .
b1001 !
b1001 -
1#
#50
0#
#55
b101 .
b111 !
b111 -
1#
#60
0#
#65
b11 .
b101 !
b101 -
1#
#70
0#
#75
b1 .
b11 !
b11 -
1#
#80
0#
#85
b1111 .
b1 !
b1 -
1#
#90
0#
#95
b1101 .
b1111 !
b1111 -
1#
#100
b1 .
0#
1"
#105
b11 .
b1 !
b1 -
1#
#110
0#
#115
b101 .
b11 !
b11 -
1#
#120
0#
#125
b111 .
b101 !
b101 -
1#
#130
0#
#135
b1001 .
b111 !
b111 -
1#
#140
0#
#145
b1011 .
b1001 !
b1001 -
1#
#150
0#
#155
b1101 .
b1011 !
b1011 -
1#
#160
0#
#165
b1111 .
b1101 !
b1101 -
1#
#170
0#
#175
b1 .
b1111 !
b1111 -
1#
#180
0#
#185
b11 .
b1 !
b1 -
1#
