HDL2/RStrA.v
module FF_T(Q, Y, clk, rst);
    output reg [3:0] Q;
    input Y, clk, rst;
    
    always @(posedge clk or negedge rst) 
    begin
        if (rst == 0) Q <= 4'b0001; 
        else 
            begin
                if (Y == 1) 
                    begin
                        if (Q == 4'b1111) Q <= 4'b0001;  
                        else Q <= Q + 4'b0010; 
                    end 
                else 
                    begin
                        if (Q == 4'b0001) Q <= 4'b1111; 
                        else Q <= Q - 4'b0010;
                    end
            end
    end
endmodule

HDL2/RStrA_tb.v
// Name: [Your Name]
// Section: [Your Section]
`timescale 1ns/1ns  

module FF_T_tb();
    reg t_Y;
    reg t_clk;
    reg t_rst;
    wire [3:0] t_Q;
    
    FF_T dut(t_Q, t_Y, t_clk, t_rst);
    
    initial begin
        t_clk = 1'b0;
        forever #5 t_clk = ~t_clk;
    end
    
    initial begin
        t_rst = 1'b0; 
        #10 t_rst = 1'b1;  
    end
    
    initial begin
        t_Y = 1'b0;
        #100 t_Y = 1'b1;  
    end
    
    initial begin
        $display("Program by [Your Name], T FF with Odd Up-Down Counter");
        $monitor("time=%03d, clk: %b, rst: %b, Y: %b, Q: %b (%d)",
                 $time, t_clk, t_rst, t_Y, t_Q, t_Q);
        $dumpfile("FF_T.vcd");
        $dumpvars();
    end
    initial #195 $finish; //#200
endmodule

HDL2/FF_T_tb.vcd
$date
	Sun Apr 06 05:09:19 2025
$end
$version
	Icarus Verilog
$end
$timescale
	1s
$end
$scope module FF_T_tb $end
$var wire 4 ! Q [3:0] $end
$var reg 1 " Y $end
$var reg 1 # clk $end
$var reg 1 $ rst $end
$scope module dut $end
$var wire 1 " Y $end
$var wire 1 # clk $end
$var wire 1 $ rst $end
$var reg 4 % Q [3:0] $end
$upscope $end
$upscope $end
$enddefinitions $end
$comment Show the parameter values. $end
$dumpall
$end
#0
$dumpvars
b1 %
0$
0#
0"
b1 !
$end
#5
1#
#10
0#
1$
#15
b11 !
b11 %
1#
#20
0#
#25
b101 !
b101 %
1#
#30
0#
#35
b111 !
b111 %
1#
#40
0#
#45
b1001 !
b1001 %
1#
#50
0#
#55
b1011 !
b1011 %
1#
#60
0#
#65
b1101 !
b1101 %
1#
#70
0#
#75
b1111 !
b1111 %
1#
#80
0#
#85
b1 !
b1 %
1#
#90
0#
1"
#95
b1111 !
b1111 %
1#
#100
0#
#105
b1101 !
b1101 %
1#
#110
0#
#115
b1011 !
b1011 %
1#
#120
0#
#125
b1001 !
b1001 %
1#
#130
0#
#135
b111 !
b111 %
1#
#140
0#
#145
b101 !
b101 %
1#
#150
0#
#155
b11 !
b11 %
1#
#160
0#
#165
b1 !
b1 %
1#
#170
0#
#175
b1111 !
b1111 %
1#
